sapsan/LinearRegression.py
sapsan/__init__.py
sapsan_ml-0.1.0.dist-info/METADATA
sapsan_ml-0.1.0.dist-info/WHEEL
sapsan_ml-0.1.0.dist-info/top_level.txt
sapsan_ml-0.1.0.dist-info/RECORD
