Metadata-Version: 2.4
Name: sapsan-ml
Version: 0.1.0
Summary: Educational ML library built from scratch
Home-page: https://github.com/твой_github/sapsan
Author: tsapuanq
Author-email: sapuantalaspai@gmail.com
Classifier: Programming Language :: Python :: 3
Classifier: License :: OSI Approved :: MIT License
Classifier: Operating System :: OS Independent
Requires-Python: >=3.7
Requires-Dist: numpy
Dynamic: author
Dynamic: author-email
Dynamic: classifier
Dynamic: description-content-type
Dynamic: home-page
Dynamic: requires-dist
Dynamic: requires-python
Dynamic: summary
